coinbase_agentkit_openai_agents_sdk/__init__.py
coinbase_agentkit_openai_agents_sdk/openai_agents_sdk_tools.py
coinbase_agentkit_openai_agents_sdk-0.7.0.dist-info/METADATA
coinbase_agentkit_openai_agents_sdk-0.7.0.dist-info/WHEEL
coinbase_agentkit_openai_agents_sdk-0.7.0.dist-info/RECORD
