Metadata-Version: 2.4
Name: coinbase-agentkit-openai-agents-sdk
Version: 0.7.0
Summary: Coinbase AgentKit OpenAI Agents SDK extension
Author-email: John Peterson <john.peterson@coinbase.com>
License-Expression: Apache-2.0
Keywords: agent,agents,ai,cdp,coinbase,crypto,openai,sdk
Requires-Python: ~=3.10
Requires-Dist: coinbase-agentkit<0.8,>=0.7.2
Requires-Dist: nest-asyncio<2,>=1.6.0
Requires-Dist: openai-agents<0.0.7,>=0.0.6
Requires-Dist: pytest-asyncio<0.26,>=0.25.3
Requires-Dist: python-dotenv<2,>=1.0.1
Requires-Dist: setuptools<70,>=69.0.3
